pqq/__about__.py
pqq/__init__.py
pqq/db.py
pqq/py.typed
pqq/queue.py
pqq/types.py
pqq-0.0.1.dist-info/METADATA
pqq-0.0.1.dist-info/WHEEL
pqq-0.0.1.dist-info/licenses/LICENSE.txt
pqq-0.0.1.dist-info/RECORD
