Metadata-Version: 2.1
Name: pqq
Version: 0.0.1
Project-URL: Documentation, https://github.com/nuxion/py-pqq#readme
Project-URL: Issues, https://github.com/nuxion/py-pqq/issues
Project-URL: Source, https://github.com/nuxion/py-pqq
Author-email: Xavier Petit <nuxion@gmail.com>
License-Expression: MIT
License-File: LICENSE.txt
Classifier: Development Status :: 4 - Beta
Classifier: Programming Language :: Python
Classifier: Programming Language :: Python :: 3.7
Classifier: Programming Language :: Python :: 3.8
Classifier: Programming Language :: Python :: 3.9
Classifier: Programming Language :: Python :: 3.10
Classifier: Programming Language :: Python :: 3.11
Classifier: Programming Language :: Python :: Implementation :: CPython
Classifier: Programming Language :: Python :: Implementation :: PyPy
Requires-Python: >=3.7
Requires-Dist: psycopg-pool~=3.1.7
Requires-Dist: psycopg[binary]~=3.1.8
Requires-Dist: pydantic
Provides-Extra: jupyter
Requires-Dist: jupyterlab~=3.6.2; extra == 'jupyter'
Requires-Dist: jupytext~=1.14.5; extra == 'jupyter'
